cemotion/__init__.py
cemotion/app.py
cemotion/dataset.py
cemotion/download.py
cemotion/models/__init__.py
cemotion/models/requirements/__init__.py
Cemotion_apple-0.3.3.dist-info/METADATA
Cemotion_apple-0.3.3.dist-info/WHEEL
Cemotion_apple-0.3.3.dist-info/top_level.txt
Cemotion_apple-0.3.3.dist-info/RECORD
