Metadata-Version: 2.1
Name: Cemotion-apple
Version: 0.3.3
Summary: 基于NLP的中文情感倾向分析库
Home-page: UNKNOWN
Author: Cyberbolt
Author-email: 735245473@qq.com
License: UNKNOWN
Platform: UNKNOWN
Classifier: Programming Language :: Python :: 3
Classifier: License :: OSI Approved :: MIT License
Classifier: Operating System :: OS Independent
Requires-Dist: tqdm (>=4.56.0)
Requires-Dist: requests (>=2.25.1)
Requires-Dist: jieba (>=0.42.1)
